wyzely_detect/__init__.py
wyzely_detect/__main__.py
wyzely_detect/utils/__init__.py
wyzely_detect/utils/cli_args.py
wyzely_detect/utils/notify.py
wyzely_detect/utils/utils.py
wyzely_detect-0.2.1.dist-info/LICENSE
wyzely_detect-0.2.1.dist-info/METADATA
wyzely_detect-0.2.1.dist-info/WHEEL
wyzely_detect-0.2.1.dist-info/entry_points.txt
wyzely_detect-0.2.1.dist-info/RECORD
