Metadata-Version: 2.1
Name: wyzely-detect
Version: 0.2.1
Summary: Recognize faces/objects in a video stream (from a webcam or a security camera) and send notifications to your devices
Home-page: https://github.com/slashtechno/wyzely-detect
License: MIT
Keywords: object-detection,face-detection,wyze,security,yolov8,unified-push
Author: slashtechno
Author-email: 77907286+slashtechno@users.noreply.github.com
Requires-Python: >=3.10,<3.12
Classifier: License :: OSI Approved :: MIT License
Classifier: Programming Language :: Python :: 3
Classifier: Programming Language :: Python :: 3.10
Classifier: Programming Language :: Python :: 3.11
Provides-Extra: cuda
Requires-Dist: absl-py (>=2.1.0,<3.0.0)
Requires-Dist: deepface (>=0.0.79,<0.0.80)
Requires-Dist: hjson (>=3.1.0,<4.0.0)
Requires-Dist: httpx (>=0.25.0,<0.26.0)
Requires-Dist: numpy (>=1.23.2,<2.0.0)
Requires-Dist: opencv-python (>=4.8.1.78,<5.0.0.0)
Requires-Dist: prettytable (>=3.9.0,<4.0.0)
Requires-Dist: python-dotenv (>=1.0.0,<2.0.0)
Requires-Dist: tensorflow (>=2.13.0,<3.0.0) ; extra != "cuda"
Requires-Dist: tensorflow-intel (>=2.13.0,<3.0.0) ; sys_platform == "win32"
Requires-Dist: tensorflow-io-gcs-filesystem (<0.32.0) ; platform_system == "Windows"
Requires-Dist: tensorflow-macos (>=2.13.0,<3.0.0) ; platform_machine == "arm64" and sys_platform == "darwin"
Requires-Dist: torch (==2.1.*) ; extra != "cuda"
Requires-Dist: ultralytics (>=8.0.190,<9.0.0)
Project-URL: Repository, https://github.com/slashtechno/wyzely-detect
